README.txt
bootstrap.py
buildout.cfg
plone25.cfg
plone3x.cfg
setup.py
docs/HISTORY.txt
docs/INSTALL.txt
docs/LICENSE.GPL
docs/LICENSE.txt
src/collective/__init__.py
src/collective.icalfeed.egg-info/PKG-INFO
src/collective.icalfeed.egg-info/SOURCES.txt
src/collective.icalfeed.egg-info/dependency_links.txt
src/collective.icalfeed.egg-info/namespace_packages.txt
src/collective.icalfeed.egg-info/not-zip-safe
src/collective.icalfeed.egg-info/requires.txt
src/collective.icalfeed.egg-info/top_level.txt
src/collective/icalfeed/__init__.py
src/collective/icalfeed/configure.zcml
src/collective/icalfeed/browser/__init__.py
src/collective/icalfeed/browser/calendar.py
src/collective/icalfeed/tests/__init__.py
src/collective/icalfeed/tests/layer.py
src/collective/icalfeed/tests/test_calendar.py