Metadata-Version: 1.0
Name: collective.icalfeed
Version: 1.0b2
Summary: View for rendering event content as an iCalendar feed.
Home-page: http://pypi.python.org/pypi/collective.icalfeed
Author: Andreas Zeidler - Plone Foundation
Author-email: plone-developers@lists.sourceforge.net
License: GPL
Keywords: plone events ical feed
Platform: Any
Classifier: Development Status :: 4 - Beta
Classifier: Environment :: Web Environment
Classifier: Framework :: Plone
Classifier: Intended Audience :: Developers
Classifier: Intended Audience :: System Administrators
Classifier: Intended Audience :: Other Audience
Classifier: License :: OSI Approved :: GNU General Public License (GPL)
Classifier: Operating System :: OS Independent
Classifier: Programming Language :: Python
Classifier: Topic :: Software Development :: Libraries :: Python Modules
